instantvideo/__init__.py
sdk/__init__.py
sdk/client.py
share/__init__.py
share/util.py
instantvideo_sdk-0.1.3.dist-info/METADATA
instantvideo_sdk-0.1.3.dist-info/WHEEL
instantvideo_sdk-0.1.3.dist-info/top_level.txt
instantvideo_sdk-0.1.3.dist-info/RECORD
