Metadata-Version: 2.4
Name: instantvideo-sdk
Version: 0.1.3
Summary: Shared utilities extracted from InstantVideo Headless for both API and SDK needs.
Author: InstantVideoHeadless Contributors
License: MIT
Classifier: Programming Language :: Python :: 3
Classifier: Programming Language :: Python :: 3.11
Classifier: Programming Language :: Python :: 3.12
Classifier: License :: OSI Approved :: MIT License
Classifier: Operating System :: OS Independent
Requires-Python: >=3.11
Requires-Dist: budoux
Requires-Dist: httpx
Requires-Dist: openrouter-provider
Requires-Dist: pydantic
Requires-Dist: research-agent-kit
Requires-Dist: textlinebreaker
